[
{
  "pk": "null", 
  "model": "desktop.document2", 
  "fields": {
    "uuid": "e63319-f120-abb1-b09b-242575abeba2", 
    "extra": "", 
    "type": "oozie-coordinator2", 
    "description": "scheduler to import midt data to HDFS raw", 
    "is_history": false, 
    "parent_directory": [
      "", 
      1, 
      false
    ], 
    "last_modified": "2017-03-12T15:42:14", 
    "version": 1, 
    "owner": [
      "scv_ops"
    ], 
    "dependencies": [ ], 
    "data": "{\"end_date\": {\"name\": \"end_date\", \"value\": \"2017-02-20T04:59\"}, \"variables\": [{\"shared_dataset_uuid\": \"\", \"is_advanced_start_instance\": false, \"show_advanced\": false, \"start_instance\": \"0\", \"timezone\": \"Asia/Dubai\", \"end_instance\": \"0\", \"same_timezone\": true, \"uuid\": \"fac36f21-045f-83ee-321a-8c6a80f3f594\", \"frequency_number\": 1, \"dataset_variable\": \"/apps/helix/controlfiles/errorlog/error_log.txt\", \"start\": \"2016-12-27T12:25\", \"same_frequency\": true, \"advanced_start_instance\": \"${coord:current(0)}\", \"advanced_end_instance\": \"${coord:current(0)}\", \"instance_choice\": \"default\", \"dataset_type\": \"parameter\", \"use_done_flag\": false, \"done_flag\": \"_SUCCESS\", \"same_start\": true, \"frequency_unit\": \"days\", \"workflow_variable\": \"ERROR_LOG_FILE\", \"is_advanced_end_instance\": false}, {\"shared_dataset_uuid\": \"\", \"is_advanced_start_instance\": false, \"show_advanced\": true, \"start_instance\": \"0\", \"timezone\": \"Asia/Dubai\", \"end_instance\": \"0\", \"same_timezone\": true, \"uuid\": \"998e05d4-1ec6-d3a0-0b3c-70b80a5d703a\", \"frequency_number\": \"1\", \"dataset_variable\": \"/data/helix/raw/midt/midt_pnr_control_file/incremental/1.0/${YEAR}-${MONTH}-${DAY}/${HOUR}-${MINUTE}\", \"start\": \"2016-12-27T12:25\", \"same_frequency\": false, \"advanced_start_instance\": \"${coord:current(0)}\", \"advanced_end_instance\": \"${coord:current(0)}\", \"instance_choice\": \"default\", \"dataset_type\": \"output_path\", \"use_done_flag\": false, \"done_flag\": \"_SUCCESS\", \"same_start\": true, \"frequency_unit\": \"days\", \"workflow_variable\": \"HDFS_PATH_PNR_CNTRL\", \"is_advanced_end_instance\": false}, {\"shared_dataset_uuid\": \"\", \"is_advanced_start_instance\": false, \"show_advanced\": false, \"start_instance\": \"0\", \"timezone\": \"Asia/Dubai\", \"end_instance\": \"0\", \"same_timezone\": true, \"uuid\": \"27ef1334-69d6-97bf-ef31-2c8e0986e470\", \"frequency_number\": 1, \"dataset_variable\": \"/apps/helix/wf_importmidt/scripts/midt_ftp_details.txt\", \"start\": \"2016-12-27T12:25\", \"same_frequency\": true, \"advanced_start_instance\": \"${coord:current(0)}\", \"advanced_end_instance\": \"${coord:current(0)}\", \"instance_choice\": \"default\", \"dataset_type\": \"parameter\", \"use_done_flag\": false, \"done_flag\": \"_SUCCESS\", \"same_start\": true, \"frequency_unit\": \"days\", \"workflow_variable\": \"FTP_DETAILS\", \"is_advanced_end_instance\": false}, {\"shared_dataset_uuid\": \"\", \"is_advanced_start_instance\": false, \"show_advanced\": false, \"start_instance\": \"0\", \"timezone\": \"Asia/Dubai\", \"end_instance\": \"0\", \"same_timezone\": true, \"uuid\": \"ae699beb-7147-ee59-599b-0846be2eccff\", \"frequency_number\": 1, \"dataset_variable\": \"/apps/helix/controlfiles/midt/midt_control.txt\", \"start\": \"2016-12-27T12:25\", \"same_frequency\": true, \"advanced_start_instance\": \"${coord:current(0)}\", \"advanced_end_instance\": \"${coord:current(0)}\", \"instance_choice\": \"default\", \"dataset_type\": \"parameter\", \"use_done_flag\": false, \"done_flag\": \"_SUCCESS\", \"same_start\": true, \"frequency_unit\": \"days\", \"workflow_variable\": \"CONTROL_FILE\", \"is_advanced_end_instance\": false}, {\"shared_dataset_uuid\": \"\", \"is_advanced_start_instance\": false, \"show_advanced\": true, \"start_instance\": \"0\", \"timezone\": \"Asia/Dubai\", \"end_instance\": \"0\", \"same_timezone\": true, \"uuid\": \"dcf5838c-8726-eae9-789e-042dc1e0a79c\", \"frequency_number\": \"1\", \"dataset_variable\": \"/data/helix/raw/midt/midt_pnr/incremental/1.0/${YEAR}-${MONTH}-${DAY}/${HOUR}-${MINUTE} \", \"start\": \"2016-12-27T12:25\", \"same_frequency\": false, \"advanced_start_instance\": \"${coord:current(0)}\", \"advanced_end_instance\": \"${coord:current(0)}\", \"instance_choice\": \"default\", \"dataset_type\": \"output_path\", \"use_done_flag\": false, \"done_flag\": \"_SUCCESS\", \"same_start\": true, \"frequency_unit\": \"days\", \"workflow_variable\": \"HDFS_PATH_MIDTPNR\", \"is_advanced_end_instance\": false}, {\"shared_dataset_uuid\": \"\", \"is_advanced_start_instance\": false, \"show_advanced\": true, \"start_instance\": \"0\", \"timezone\": \"Asia/Dubai\", \"end_instance\": \"0\", \"same_timezone\": true, \"uuid\": \"a88618b5-ea58-c2ae-cd30-e65c0f550649\", \"frequency_number\": \"1\", \"dataset_variable\": \"/data/helix/raw/midt/gds_agent_master/incremental/1.0/${YEAR}-${MONTH}-${DAY}/${HOUR}-${MINUTE}\", \"start\": \"2016-12-27T12:25\", \"same_frequency\": false, \"advanced_start_instance\": \"${coord:current(0)}\", \"advanced_end_instance\": \"${coord:current(0)}\", \"instance_choice\": \"default\", \"dataset_type\": \"output_path\", \"use_done_flag\": false, \"done_flag\": \"_SUCCESS\", \"same_start\": true, \"frequency_unit\": \"days\", \"workflow_variable\": \"HDFS_PATH_AGENT_MSTR\", \"is_advanced_end_instance\": false}, {\"shared_dataset_uuid\": \"\", \"is_advanced_start_instance\": false, \"show_advanced\": true, \"start_instance\": \"0\", \"timezone\": \"Asia/Dubai\", \"end_instance\": \"0\", \"same_timezone\": true, \"uuid\": \"f7f88cef-3956-35fc-12ba-5f4c6c54dba6\", \"frequency_number\": \"1\", \"dataset_variable\": \"/data/helix/raw/midt/gds_agent_master_control_file/incremental/1.0/${YEAR}-${MONTH}-${DAY}/${HOUR}-${MINUTE}\", \"start\": \"2016-12-27T12:25\", \"same_frequency\": false, \"advanced_start_instance\": \"${coord:current(0)}\", \"advanced_end_instance\": \"${coord:current(0)}\", \"instance_choice\": \"default\", \"dataset_type\": \"output_path\", \"use_done_flag\": false, \"done_flag\": \"_SUCCESS\", \"same_start\": true, \"frequency_unit\": \"days\", \"workflow_variable\": \"HDFS_PATH_AGENT_CNTRL\", \"is_advanced_end_instance\": false}, {\"shared_dataset_uuid\": \"\", \"is_advanced_start_instance\": false, \"show_advanced\": false, \"start_instance\": \"0\", \"timezone\": \"Asia/Dubai\", \"end_instance\": \"0\", \"same_timezone\": true, \"uuid\": \"532c867a-ea6e-c04d-f182-d2461fea85b8\", \"frequency_number\": 1, \"dataset_variable\": \"/data/1/share/midt/files\", \"start\": \"2016-12-27T12:25\", \"same_frequency\": true, \"advanced_start_instance\": \"${coord:current(0)}\", \"advanced_end_instance\": \"${coord:current(0)}\", \"instance_choice\": \"default\", \"dataset_type\": \"parameter\", \"use_done_flag\": false, \"done_flag\": \"_SUCCESS\", \"same_start\": true, \"frequency_unit\": \"days\", \"workflow_variable\": \"LOCAL_DIR\", \"is_advanced_end_instance\": false}, {\"shared_dataset_uuid\": \"\", \"is_advanced_start_instance\": false, \"show_advanced\": false, \"start_instance\": \"0\", \"timezone\": \"Asia/Dubai\", \"end_instance\": \"0\", \"same_timezone\": true, \"uuid\": \"e4db751c-baae-1ed6-667e-71737b4f571b\", \"frequency_number\": 1, \"dataset_variable\": \"/data/1/share/midt/work\", \"start\": \"2016-12-27T12:25\", \"same_frequency\": true, \"advanced_start_instance\": \"${coord:current(0)}\", \"advanced_end_instance\": \"${coord:current(0)}\", \"instance_choice\": \"default\", \"dataset_type\": \"parameter\", \"use_done_flag\": false, \"done_flag\": \"_SUCCESS\", \"same_start\": true, \"frequency_unit\": \"days\", \"workflow_variable\": \"WRK_DIR\", \"is_advanced_end_instance\": false}, {\"shared_dataset_uuid\": \"\", \"is_advanced_start_instance\": false, \"show_advanced\": false, \"start_instance\": \"0\", \"timezone\": \"Asia/Dubai\", \"end_instance\": \"0\", \"same_timezone\": true, \"uuid\": \"4c126ce4-e51c-5f76-6e8c-c44b9a31e17f\", \"frequency_number\": 1, \"dataset_variable\": \"23\", \"start\": \"2017-02-26T15:21\", \"same_frequency\": true, \"advanced_start_instance\": \"${coord:current(0)}\", \"advanced_end_instance\": \"${coord:current(0)}\", \"instance_choice\": \"default\", \"dataset_type\": \"parameter\", \"use_done_flag\": false, \"done_flag\": \"_SUCCESS\", \"same_start\": true, \"frequency_unit\": \"days\", \"workflow_variable\": \"HOURCHECK\", \"is_advanced_end_instance\": false}], \"isDirty\": false, \"showAdvancedFrequencyUI\": true, \"variablesUI\": [\"parameter\", \"input_path\", \"output_path\"], \"workflowParameters\": [{\"name\": \"ERROR_LOG_FILE\", \"value\": \"\"}, {\"name\": \"HDFS_PATH_PNR_CNTRL\", \"value\": \"\"}, {\"name\": \"FTP_DETAILS\", \"value\": \"\"}, {\"name\": \"CONTROL_FILE\", \"value\": \"\"}, {\"name\": \"HDFS_PATH_MIDTPNR\", \"value\": \"\"}, {\"name\": \"HDFS_PATH_AGENT_MSTR\", \"value\": \"\"}, {\"name\": \"HDFS_PATH_AGENT_CNTRL\", \"value\": \"\"}, {\"name\": \"LOCAL_DIR\", \"value\": \"\"}, {\"name\": \"WRK_DIR\", \"value\": \"\"}, {\"name\": \"HOURCHECK\", \"value\": \"HOURCHECK\"}], \"properties\": {\"job_xml\": \"\", \"timeout\": null, \"execution\": \"FIFO\", \"end\": \"${end_date}\", \"description\": \"scheduler to import midt data to HDFS raw\", \"frequency_number\": 1, \"workflow\": \"3a705d6f-b9ef-473d-80c9-343464224682\", \"deployment_dir\": \"/user/hue/oozie/workspaces/hue-oozie-1482827112.0\", \"cron_frequency\": \"33 * * * *\", \"frequency_unit\": \"days\", \"schema_version\": \"uri:oozie:coordinator:0.2\", \"cron_advanced\": false, \"start\": \"${start_date}\", \"concurrency\": 0, \"timezone\": \"Asia/Dubai\", \"credentials\": [], \"throttle\": 0, \"parameters\": [{\"name\": \"oozie.use.system.libpath\", \"value\": true}, {\"name\": \"start_date\", \"value\": \"2017-02-20T04:00\"}, {\"name\": \"end_date\", \"value\": \"2017-02-20T04:59\"}], \"sla\": [{\"key\": \"enabled\", \"value\": false}, {\"key\": \"nominal-time\", \"value\": \"${nominal_time}\"}, {\"key\": \"should-start\", \"value\": \"\"}, {\"key\": \"should-end\", \"value\": \"${30 * MINUTES}\"}, {\"key\": \"max-duration\", \"value\": \"\"}, {\"key\": \"alert-events\", \"value\": \"\"}, {\"key\": \"alert-contact\", \"value\": \"\"}, {\"key\": \"notification-msg\", \"value\": \"\"}, {\"key\": \"upstream-apps\", \"value\": \"\"}]}, \"uuid\": \"e63317a9-f120-abb1-b09b-242575abeba2\", \"name\": \"weeklyimportmidt\", \"id\": 54968, \"start_date\": {\"name\": \"start_date\", \"value\": \"2017-02-20T04:00\"}}", 
    "name": "weeklyimportmidt"
  }
}
]
