[
{
  "pk": null, 
  "model": "desktop.document2", 
  "fields": {
    "uuid": "fd9cd886-bb5d-8a8f-41d0-5642d6364196", 
    "extra": "", 
    "type": "oozie-workflow2", 
    "description": "Transfers historical FARE_BASIS_CODE_LIST data from HDFS Raw to HDFS Decomposed", 
    "is_history": false, 
    "parent_directory": [
      "", 
      1, 
      false
    ], 
    "last_modified": "2017-05-09T09:25:44", 
    "version": 1, 
    "owner": [
      "scv_ops"
    ], 
    "dependencies": [], 
    "data": "{\"layout\": [{\"oozieRows\": [{\"enableOozieDropOnBefore\": true, \"enableOozieDropOnSide\": true, \"enableOozieDrop\": false, \"widgets\": [{\"status\": \"\", \"logsURL\": \"\", \"name\": \"Shell\", \"widgetType\": \"shell-widget\", \"oozieMovable\": true, \"ooziePropertiesExpanded\": false, \"externalIdUrl\": \"\", \"properties\": {}, \"isLoading\": true, \"offset\": 0, \"actionURL\": \"\", \"progress\": 0, \"klass\": \"card card-widget span12\", \"oozieExpanded\": false, \"id\": \"fda496bc-7a9c-8dbe-8be8-1c0558ea141e\", \"size\": 12}], \"id\": \"df0bc45c-7710-8595-25f6-7b3cbbc1ebcc\", \"columns\": []}, {\"enableOozieDropOnBefore\": true, \"enableOozieDropOnSide\": true, \"enableOozieDrop\": false, \"widgets\": [{\"status\": \"\", \"logsURL\": \"\", \"name\": \"Pig Script\", \"widgetType\": \"pig-widget\", \"oozieMovable\": true, \"ooziePropertiesExpanded\": false, \"externalIdUrl\": \"\", \"properties\": {}, \"isLoading\": true, \"offset\": 0, \"actionURL\": \"\", \"progress\": 0, \"klass\": \"card card-widget span12\", \"oozieExpanded\": false, \"id\": \"820c3330-a79d-a0f5-9598-283e2ee9377c\", \"size\": 12}], \"id\": \"04733fbf-0ad4-7762-052c-cb97b58b0901\", \"columns\": []}, {\"enableOozieDropOnBefore\": true, \"enableOozieDropOnSide\": true, \"enableOozieDrop\": false, \"widgets\": [{\"status\": \"\", \"logsURL\": \"\", \"name\": \"Email\", \"widgetType\": \"email-widget\", \"oozieMovable\": true, \"ooziePropertiesExpanded\": false, \"externalIdUrl\": \"\", \"properties\": {}, \"isLoading\": true, \"offset\": 0, \"actionURL\": \"\", \"progress\": 0, \"klass\": \"card card-widget span12\", \"oozieExpanded\": false, \"id\": \"f627b96d-d877-3a3b-c3a5-9ea4216fc0f4\", \"size\": 12}], \"id\": \"311c9acf-9b94-828d-1878-7e5d7efd878d\", \"columns\": []}], \"rows\": [{\"enableOozieDropOnBefore\": true, \"enableOozieDropOnSide\": true, \"enableOozieDrop\": false, \"widgets\": [{\"status\": \"\", \"logsURL\": \"\", \"name\": \"Start\", \"widgetType\": \"start-widget\", \"oozieMovable\": false, \"ooziePropertiesExpanded\": false, \"externalIdUrl\": \"\", \"properties\": {}, \"isLoading\": true, \"offset\": 0, \"actionURL\": \"\", \"progress\": 0, \"klass\": \"card card-widget span12\", \"oozieExpanded\": false, \"id\": \"3f107997-04cc-8733-60a9-a4bb62cebffc\", \"size\": 12}], \"id\": \"8cca95a6-3978-ba83-21f1-981f51f9a08b\", \"columns\": []}, {\"enableOozieDropOnBefore\": true, \"enableOozieDropOnSide\": true, \"enableOozieDrop\": false, \"widgets\": [{\"status\": \"\", \"logsURL\": \"\", \"name\": \"Shell\", \"widgetType\": \"shell-widget\", \"oozieMovable\": true, \"ooziePropertiesExpanded\": false, \"externalIdUrl\": \"\", \"properties\": {}, \"isLoading\": true, \"offset\": 0, \"actionURL\": \"\", \"progress\": 0, \"klass\": \"card card-widget span12\", \"oozieExpanded\": false, \"id\": \"fda496bc-7a9c-8dbe-8be8-1c0558ea141e\", \"size\": 12}], \"id\": \"df0bc45c-7710-8595-25f6-7b3cbbc1ebcc\", \"columns\": []}, {\"enableOozieDropOnBefore\": true, \"enableOozieDropOnSide\": true, \"enableOozieDrop\": false, \"widgets\": [{\"status\": \"\", \"logsURL\": \"\", \"name\": \"Pig Script\", \"widgetType\": \"pig-widget\", \"oozieMovable\": true, \"ooziePropertiesExpanded\": false, \"externalIdUrl\": \"\", \"properties\": {}, \"isLoading\": true, \"offset\": 0, \"actionURL\": \"\", \"progress\": 0, \"klass\": \"card card-widget span12\", \"oozieExpanded\": false, \"id\": \"820c3330-a79d-a0f5-9598-283e2ee9377c\", \"size\": 12}], \"id\": \"04733fbf-0ad4-7762-052c-cb97b58b0901\", \"columns\": []}, {\"enableOozieDropOnBefore\": true, \"enableOozieDropOnSide\": true, \"enableOozieDrop\": false, \"widgets\": [{\"status\": \"\", \"logsURL\": \"\", \"name\": \"Email\", \"widgetType\": \"email-widget\", \"oozieMovable\": true, \"ooziePropertiesExpanded\": false, \"externalIdUrl\": \"\", \"properties\": {}, \"isLoading\": true, \"offset\": 0, \"actionURL\": \"\", \"progress\": 0, \"klass\": \"card card-widget span12\", \"oozieExpanded\": false, \"id\": \"f627b96d-d877-3a3b-c3a5-9ea4216fc0f4\", \"size\": 12}], \"id\": \"311c9acf-9b94-828d-1878-7e5d7efd878d\", \"columns\": []}, {\"enableOozieDropOnBefore\": true, \"enableOozieDropOnSide\": true, \"enableOozieDrop\": false, \"widgets\": [{\"status\": \"\", \"logsURL\": \"\", \"name\": \"End\", \"widgetType\": \"end-widget\", \"oozieMovable\": false, \"ooziePropertiesExpanded\": false, \"externalIdUrl\": \"\", \"properties\": {}, \"isLoading\": true, \"offset\": 0, \"actionURL\": \"\", \"progress\": 0, \"klass\": \"card card-widget span12\", \"oozieExpanded\": false, \"id\": \"33430f0f-ebfa-c3ec-f237-3e77efa03d0a\", \"size\": 12}], \"id\": \"381152f2-fc41-8e12-aada-416efd742bd7\", \"columns\": []}, {\"enableOozieDropOnBefore\": true, \"enableOozieDropOnSide\": true, \"enableOozieDrop\": false, \"widgets\": [{\"status\": \"\", \"logsURL\": \"\", \"name\": \"Kill\", \"widgetType\": \"kill-widget\", \"oozieMovable\": true, \"ooziePropertiesExpanded\": false, \"externalIdUrl\": \"\", \"properties\": {}, \"isLoading\": true, \"offset\": 0, \"actionURL\": \"\", \"progress\": 0, \"klass\": \"card card-widget span12\", \"oozieExpanded\": false, \"id\": \"17c9c895-5a16-7443-bb81-f34b30b21548\", \"size\": 12}], \"id\": \"aeed9eee-87b1-a987-975d-1d530bc46a27\", \"columns\": []}], \"oozieEndRow\": {\"enableOozieDropOnBefore\": true, \"enableOozieDropOnSide\": true, \"enableOozieDrop\": false, \"widgets\": [{\"status\": \"\", \"logsURL\": \"\", \"name\": \"End\", \"widgetType\": \"end-widget\", \"oozieMovable\": false, \"ooziePropertiesExpanded\": false, \"externalIdUrl\": \"\", \"properties\": {}, \"isLoading\": true, \"offset\": 0, \"actionURL\": \"\", \"progress\": 0, \"klass\": \"card card-widget span12\", \"oozieExpanded\": false, \"id\": \"33430f0f-ebfa-c3ec-f237-3e77efa03d0a\", \"size\": 12}], \"id\": \"381152f2-fc41-8e12-aada-416efd742bd7\", \"columns\": []}, \"oozieKillRow\": {\"enableOozieDropOnBefore\": true, \"enableOozieDropOnSide\": true, \"enableOozieDrop\": false, \"widgets\": [{\"status\": \"\", \"logsURL\": \"\", \"name\": \"Kill\", \"widgetType\": \"kill-widget\", \"oozieMovable\": true, \"ooziePropertiesExpanded\": false, \"externalIdUrl\": \"\", \"properties\": {}, \"isLoading\": true, \"offset\": 0, \"actionURL\": \"\", \"progress\": 0, \"klass\": \"card card-widget span12\", \"oozieExpanded\": false, \"id\": \"17c9c895-5a16-7443-bb81-f34b30b21548\", \"size\": 12}], \"id\": \"aeed9eee-87b1-a987-975d-1d530bc46a27\", \"columns\": []}, \"enableOozieDropOnAfter\": true, \"oozieStartRow\": {\"enableOozieDropOnBefore\": true, \"enableOozieDropOnSide\": true, \"enableOozieDrop\": false, \"widgets\": [{\"status\": \"\", \"logsURL\": \"\", \"name\": \"Start\", \"widgetType\": \"start-widget\", \"oozieMovable\": false, \"ooziePropertiesExpanded\": false, \"externalIdUrl\": \"\", \"properties\": {}, \"isLoading\": true, \"offset\": 0, \"actionURL\": \"\", \"progress\": 0, \"klass\": \"card card-widget span12\", \"oozieExpanded\": false, \"id\": \"3f107997-04cc-8733-60a9-a4bb62cebffc\", \"size\": 12}], \"id\": \"8cca95a6-3978-ba83-21f1-981f51f9a08b\", \"columns\": []}, \"klass\": \"card card-home card-column span12\", \"enableOozieDropOnBefore\": true, \"drops\": [\"temp\"], \"id\": \"5ec7d5d7-e954-1da2-2525-4e93b19f77a3\", \"size\": 12}], \"workflow\": {\"properties\": {\"job_xml\": \"\", \"description\": \"Transfers historical FARE_BASIS_CODE_LIST data from HDFS Raw to HDFS Decomposed\", \"parameters\": [{\"name\": \"oozie.use.system.libpath\", \"value\": true}], \"sla_enabled\": false, \"deployment_dir\": \"/apps/helix/conf/oozie/workspaces/wf_RawToDecomposedFBCL_History\", \"schema_version\": \"uri:oozie:workflow:0.5\", \"properties\": [{\"name\": \"oozie.launcher.mapreduce.job.queuename\", \"value\": \"cbi_ops\"}, {\"name\": \"mapreduce.job.queuename\", \"value\": \"cbi_ops\"}], \"show_arrows\": true, \"wf1_id\": null, \"sla\": [{\"key\": \"enabled\", \"value\": false}, {\"key\": \"nominal-time\", \"value\": \"${nominal_time}\"}, {\"key\": \"should-start\", \"value\": \"\"}, {\"key\": \"should-end\", \"value\": \"${30 * MINUTES}\"}, {\"key\": \"max-duration\", \"value\": \"\"}, {\"key\": \"alert-events\", \"value\": \"\"}, {\"key\": \"alert-contact\", \"value\": \"\"}, {\"key\": \"notification-msg\", \"value\": \"\"}, {\"key\": \"upstream-apps\", \"value\": \"\"}]}, \"name\": \"RawToDecomposedFBCL_History\", \"versions\": [\"uri:oozie:workflow:0.4\", \"uri:oozie:workflow:0.4.5\", \"uri:oozie:workflow:0.5\"], \"isDirty\": true, \"movedNode\": null, \"linkMapping\": {\"17c9c895-5a16-7443-bb81-f34b30b21548\": [], \"f627b96d-d877-3a3b-c3a5-9ea4216fc0f4\": [\"17c9c895-5a16-7443-bb81-f34b30b21548\"], \"820c3330-a79d-a0f5-9598-283e2ee9377c\": [\"33430f0f-ebfa-c3ec-f237-3e77efa03d0a\"], \"fda496bc-7a9c-8dbe-8be8-1c0558ea141e\": [\"820c3330-a79d-a0f5-9598-283e2ee9377c\"], \"33430f0f-ebfa-c3ec-f237-3e77efa03d0a\": [], \"3f107997-04cc-8733-60a9-a4bb62cebffc\": [\"fda496bc-7a9c-8dbe-8be8-1c0558ea141e\"]}, \"nodeIds\": [\"3f107997-04cc-8733-60a9-a4bb62cebffc\", \"33430f0f-ebfa-c3ec-f237-3e77efa03d0a\", \"17c9c895-5a16-7443-bb81-f34b30b21548\", \"fda496bc-7a9c-8dbe-8be8-1c0558ea141e\", \"820c3330-a79d-a0f5-9598-283e2ee9377c\", \"f627b96d-d877-3a3b-c3a5-9ea4216fc0f4\"], \"nodes\": [{\"properties\": {}, \"name\": \"Start\", \"children\": [{\"to\": \"fda496bc-7a9c-8dbe-8be8-1c0558ea141e\"}], \"actionParametersFetched\": false, \"type\": \"start-widget\", \"id\": \"3f107997-04cc-8733-60a9-a4bb62cebffc\", \"actionParameters\": []}, {\"properties\": {}, \"name\": \"End\", \"children\": [], \"actionParametersFetched\": false, \"type\": \"end-widget\", \"id\": \"33430f0f-ebfa-c3ec-f237-3e77efa03d0a\", \"actionParameters\": []}, {\"properties\": {\"body\": \"\", \"cc\": \"\", \"to\": \"\", \"enableMail\": false, \"message\": \"Action failed, error message[${wf:errorMessage(wf:lastErrorNode())}]\", \"subject\": \"\"}, \"name\": \"Kill\", \"children\": [], \"actionParametersFetched\": false, \"type\": \"kill-widget\", \"id\": \"17c9c895-5a16-7443-bb81-f34b30b21548\", \"actionParameters\": []}, {\"properties\": {\"files\": [{\"value\": \"read_avro_schema.sh\"}], \"job_xml\": \"\", \"retry_interval\": [], \"retry_max\": [], \"job_properties\": [], \"capture_output\": true, \"shell_command\": \"read_avro_schema.sh\", \"arguments\": [{\"value\": \"${T_S_FARE_BASIS_CODE_LIST}\"}], \"prepares\": [], \"credentials\": [], \"env_var\": [], \"sla\": [{\"key\": \"enabled\", \"value\": false}, {\"key\": \"nominal-time\", \"value\": \"${nominal_time}\"}, {\"key\": \"should-start\", \"value\": \"\"}, {\"key\": \"should-end\", \"value\": \"${30 * MINUTES}\"}, {\"key\": \"max-duration\", \"value\": \"\"}, {\"key\": \"alert-events\", \"value\": \"\"}, {\"key\": \"alert-contact\", \"value\": \"\"}, {\"key\": \"notification-msg\", \"value\": \"\"}, {\"key\": \"upstream-apps\", \"value\": \"\"}], \"archives\": []}, \"name\": \"shell-fda4\", \"children\": [{\"to\": \"820c3330-a79d-a0f5-9598-283e2ee9377c\"}, {\"error\": \"f627b96d-d877-3a3b-c3a5-9ea4216fc0f4\"}], \"actionParametersFetched\": false, \"type\": \"shell-widget\", \"id\": \"fda496bc-7a9c-8dbe-8be8-1c0558ea141e\", \"actionParameters\": []}, {\"name\": \"pig-820c\", \"actionParametersUI\": [], \"children\": [{\"to\": \"33430f0f-ebfa-c3ec-f237-3e77efa03d0a\"}, {\"error\": \"f627b96d-d877-3a3b-c3a5-9ea4216fc0f4\"}], \"properties\": {\"files\": [{\"value\": \"RawToDecomposed.pig\"}, {\"value\": \"pigudf.jar\"}], \"job_xml\": [], \"parameters\": [{\"value\": \"SOURCE_DIRECTORY=${S_D_FARE_BASIS_CODE_LIST}\"}, {\"value\": \"SOURCE_SCHEMA_FILE=${S_S_FARE_BASIS_CODE_LIST}\"}, {\"value\": \"TARGET_DIRECTORY=${T_D_FARE_BASIS_CODE_LIST}\"}, {\"value\": \"TARGET_SCHEMA=${wf:actionData('shell-fda4')['AVRO_SCHEMA']}\"}], \"retry_interval\": [], \"retry_max\": [], \"job_properties\": [], \"arguments\": [], \"prepares\": [{\"type\": \"delete\", \"value\": \"${T_D_FARE_BASIS_CODE_LIST}\"}], \"credentials\": [], \"script_path\": \"RawToDecomposed.pig\", \"sla\": [{\"key\": \"enabled\", \"value\": false}, {\"key\": \"nominal-time\", \"value\": \"${nominal_time}\"}, {\"key\": \"should-start\", \"value\": \"\"}, {\"key\": \"should-end\", \"value\": \"${30 * MINUTES}\"}, {\"key\": \"max-duration\", \"value\": \"\"}, {\"key\": \"alert-events\", \"value\": \"\"}, {\"key\": \"alert-contact\", \"value\": \"\"}, {\"key\": \"notification-msg\", \"value\": \"\"}, {\"key\": \"upstream-apps\", \"value\": \"\"}], \"archives\": []}, \"actionParametersFetched\": false, \"type\": \"pig-widget\", \"id\": \"820c3330-a79d-a0f5-9598-283e2ee9377c\", \"actionParameters\": []}, {\"properties\": {\"body\": \"Current timestamp: ${timestamp()}\\nWorkflow name: ${wf:name()}\\nWorkflow id: ${wf:id()}\\nWorkflow application path: ${wf:appPath()}\\nWorkflow user: ${wf:user()}\\nLast error action: ${wf:lastErrorNode()}\\nError code: ${wf:errorCode(wf:lastErrorNode())}\\nError message: ${wf:errorMessage(wf:lastErrorNode())}\\n\", \"cc\": \"\", \"retry_interval\": [], \"retry_max\": [], \"bcc\": \"\", \"to\": \"spike.jensen@emirates.com\", \"attachment\": \"\", \"content_type\": \"text/plain\", \"credentials\": [], \"sla\": [{\"key\": \"enabled\", \"value\": false}, {\"key\": \"nominal-time\", \"value\": \"${nominal_time}\"}, {\"key\": \"should-start\", \"value\": \"\"}, {\"key\": \"should-end\", \"value\": \"${30 * MINUTES}\"}, {\"key\": \"max-duration\", \"value\": \"\"}, {\"key\": \"alert-events\", \"value\": \"\"}, {\"key\": \"alert-contact\", \"value\": \"\"}, {\"key\": \"notification-msg\", \"value\": \"\"}, {\"key\": \"upstream-apps\", \"value\": \"\"}], \"subject\": \"Workflow ${wf:name()} failed\"}, \"name\": \"email-f627\", \"children\": [{\"to\": \"17c9c895-5a16-7443-bb81-f34b30b21548\"}, {\"error\": \"17c9c895-5a16-7443-bb81-f34b30b21548\"}], \"actionParametersFetched\": false, \"type\": \"email-widget\", \"id\": \"f627b96d-d877-3a3b-c3a5-9ea4216fc0f4\", \"actionParameters\": []}], \"id\": 124287, \"nodeNamesMapping\": {\"17c9c895-5a16-7443-bb81-f34b30b21548\": \"Kill\", \"f627b96d-d877-3a3b-c3a5-9ea4216fc0f4\": \"email-f627\", \"820c3330-a79d-a0f5-9598-283e2ee9377c\": \"pig-820c\", \"fda496bc-7a9c-8dbe-8be8-1c0558ea141e\": \"shell-fda4\", \"33430f0f-ebfa-c3ec-f237-3e77efa03d0a\": \"End\", \"3f107997-04cc-8733-60a9-a4bb62cebffc\": \"Start\"}, \"uuid\": \"fd9cd886-bb5d-8a8f-41d0-5642d6364196\"}}", 
    "name": "RawToDecomposedFBCL_History"
  }
}
]
